thread_order/__init__.py
thread_order/graph.py
thread_order/graph_summary.py
thread_order/logger.py
thread_order/runner.py
thread_order/scheduler.py
thread_order/timer.py
thread_order-1.0.1.dist-info/licenses/LICENSE
thread_order-1.0.1.dist-info/METADATA
thread_order-1.0.1.dist-info/WHEEL
thread_order-1.0.1.dist-info/entry_points.txt
thread_order-1.0.1.dist-info/top_level.txt
thread_order-1.0.1.dist-info/RECORD
