Metadata-Version: 2.4
Name: thread-order
Version: 1.0.1
Summary: A lightweight framework for running functions concurrently across multiple threads while maintaining a defined execution order.
Author-email: Emilio Reyes <soda480@gmail.com>
License-Expression: Apache-2.0
Project-URL: Homepage, https://github.com/soda480/thread-order
Classifier: Development Status :: 4 - Beta
Classifier: Environment :: Console
Classifier: Intended Audience :: Developers
Classifier: Operating System :: OS Independent
Classifier: Programming Language :: Python
Classifier: Programming Language :: Python :: 3
Classifier: Programming Language :: Python :: 3 :: Only
Classifier: Programming Language :: Python :: 3.9
Classifier: Programming Language :: Python :: 3.10
Classifier: Programming Language :: Python :: 3.11
Classifier: Programming Language :: Python :: 3.12
Classifier: Topic :: Software Development
Classifier: Topic :: Software Development :: Libraries
Classifier: Topic :: Software Development :: Libraries :: Python Modules
Classifier: Topic :: Software Development :: Testing
Classifier: Topic :: Utilities
Requires-Python: >=3.9
License-File: LICENSE
Requires-Dist: colorama
Provides-Extra: dev
Requires-Dist: build; extra == "dev"
Requires-Dist: flake8; extra == "dev"
Requires-Dist: mock; extra == "dev"
Requires-Dist: radon; extra == "dev"
Requires-Dist: bandit; extra == "dev"
Requires-Dist: coverage; extra == "dev"
Requires-Dist: coverage-badge; extra == "dev"
Requires-Dist: twine; extra == "dev"
Dynamic: license-file
